<annotation>
	<folder>karisik</folder>
	<filename>mep (47).jpeg</filename>
	<path>C:\Users\goktu\OneDrive\Desktop\karisik\mep (47).jpeg</path>
	<source>
		<database>Unknown</database>
	</source>
	<size>
		<width>960</width>
		<height>540</height>
		<depth>3</depth>
	</size>
	<segmented>0</segmented>
	<object>
		<name>muz</name>
		<pose>Unspecified</pose>
		<truncated>0</truncated>
		<difficult>0</difficult>
		<bndbox>
			<xmin>151</xmin>
			<ymin>120</ymin>
			<xmax>748</xmax>
			<ymax>194</ymax>
		</bndbox>
	</object>
	<object>
		<name>muz</name>
		<pose>Unspecified</pose>
		<truncated>0</truncated>
		<difficult>0</difficult>
		<bndbox>
			<xmin>623</xmin>
			<ymin>224</ymin>
			<xmax>889</xmax>
			<ymax>355</ymax>
		</bndbox>
	</object>
	<object>
		<name>elma</name>
		<pose>Unspecified</pose>
		<truncated>0</truncated>
		<difficult>0</difficult>
		<bndbox>
			<xmin>512</xmin>
			<ymin>206</ymin>
			<xmax>704</xmax>
			<ymax>259</ymax>
		</bndbox>
	</object>
	<object>
		<name>elma</name>
		<pose>Unspecified</pose>
		<truncated>0</truncated>
		<difficult>0</difficult>
		<bndbox>
			<xmin>418</xmin>
			<ymin>275</ymin>
			<xmax>599</xmax>
			<ymax>328</ymax>
		</bndbox>
	</object>
	<object>
		<name>portakal</name>
		<pose>Unspecified</pose>
		<truncated>0</truncated>
		<difficult>0</difficult>
		<bndbox>
			<xmin>170</xmin>
			<ymin>294</ymin>
			<xmax>375</xmax>
			<ymax>353</ymax>
		</bndbox>
	</object>
	<object>
		<name>portakal</name>
		<pose>Unspecified</pose>
		<truncated>0</truncated>
		<difficult>0</difficult>
		<bndbox>
			<xmin>190</xmin>
			<ymin>215</ymin>
			<xmax>379</xmax>
			<ymax>266</ymax>
		</bndbox>
	</object>
</annotation>
